pyrameters/Subsection.py
pyrameters/__init__.py
pyrameters/prm.py
pyrameters-0.0.1.dist-info/LICENSE
pyrameters-0.0.1.dist-info/METADATA
pyrameters-0.0.1.dist-info/WHEEL
pyrameters-0.0.1.dist-info/top_level.txt
pyrameters-0.0.1.dist-info/RECORD
