Metadata-Version: 2.1
Name: pyrameters
Version: 0.0.1
Summary: Read, edit, and output parameters for scientific software.
Home-page: https://github.com/jperryhouts/pyrameters
Author: Jonathan Perry-Houts
Author-email: jon@than.ph
License: UNKNOWN
Platform: UNKNOWN
Classifier: Programming Language :: Python :: 3
Classifier: License :: OSI Approved :: GNU General Public License v3 or later (GPLv3+)
Classifier: Operating System :: OS Independent
Requires-Python: >=3.6
